dotml/__init__.py
dotml/cli.py
dotml/compiler.py
dotml/cube.py
dotml-0.1.9.dist-info/LICENSE
dotml-0.1.9.dist-info/METADATA
dotml-0.1.9.dist-info/WHEEL
dotml-0.1.9.dist-info/entry_points.txt
dotml-0.1.9.dist-info/top_level.txt
dotml-0.1.9.dist-info/RECORD
