Metadata-Version: 2.1
Name: dotml
Version: 0.1.9
License-File: LICENSE
Requires-Dist: pyyaml
Requires-Dist: typer
Requires-Dist: json5
